{
  "version": "2.0",
  "topic": {
    "title": "Root Keys",
    "category": "Cybersecurity",
    "domain": "Security Architecture And Engineering",
    "subdomain": "Cryptographic Solutions",
    "entry_domain": "Key Management",
    "entry_subdomain": "Key Types and Hierarchy"
  },
  "voting": {
    "consensus_reached": true,
    "approval_percentage": 0.671,
    "positive_votes": 5,
    "total_votes": 7,
    "voter_breakdown": [
      {
        "voter": "Pedagogy Specialist",
        "decision": "revise",
        "confidence": 0.9
      },
      {
        "voter": "Active Learning Designer",
        "decision": "approve_with_suggestions",
        "confidence": 0.92
      },
      {
        "voter": "Scaffolding Expert",
        "decision": "revise",
        "confidence": 0.85
      },
      {
        "voter": "Connection Mapper",
        "decision": "approve_with_suggestions",
        "confidence": 0.9
      },
      {
        "voter": "Assessment Designer",
        "decision": "approve_with_suggestions",
        "confidence": 0.88
      },
      {
        "voter": "Clarity Editor",
        "decision": "approve_with_suggestions",
        "confidence": 0.95
      },
      {
        "voter": "Schema Validator",
        "decision": "approve_with_suggestions",
        "confidence": 0.92
      }
    ]
  },
  "learning_objectives": [
    {
      "level": "remember",
      "objective": "Define key terminology"
    },
    {
      "level": "understand",
      "objective": "Explain core concepts"
    },
    {
      "level": "apply",
      "objective": "Apply knowledge to scenarios"
    },
    {
      "level": "analyze",
      "objective": "Analyze relationships"
    }
  ],
  "scaffolding_layers": 4,
  "exa_sources": 0,
  "generation_timestamp": "2026-01-01T14:14:57.515376"
}