{
  "subdomain_title": "SNMP (Simple Network Management Protocol)",
  "domain_title": "Network Services and Infrastructure",
  "category_title": null,
  "curriculum_type": "network-engineering",
  "processed_at": "2025-12-29T13:41:20.484286",
  "result": {
    "subdomain_title": "SNMP (Simple Network Management Protocol)",
    "curriculum_type": "network-engineering",
    "topic_root": "SNMP (Simple Network Management Protocol)",
    "topic_root_citation": "https://datatracker.ietf.org/doc/html/rfc3411/",
    "detailed_hierarchy": [
      {
        "domain": "SNMP Fundamentals",
        "sub_domains": [
          {
            "sub_domain": "Protocol Overview and History",
            "atomic_topics": [
              "Definition and Purpose of SNMP",
              "SNMP as an Internet Standard Protocol",
              "Evolution from SNMPv1 to SNMPv3",
              "IETF RFC Standards and Documentation",
              "Application Layer Protocol in TCP/IP Stack",
              "Manager/Agent Architecture Model",
              "Network Management Station (NMS) Role"
            ]
          },
          {
            "sub_domain": "SNMP Architecture and Components",
            "atomic_topics": [
              "SNMP Entity Structure",
              "SNMP Engine Components",
              "SNMP Manager (NMS) Functionality",
              "SNMP Agent Software",
              "Dispatcher Component",
              "Message Processing Subsystem",
              "Security Subsystem",
              "Access Control Subsystem",
              "Application Types (Command Generator, Responder, etc.)",
              "Proxy Agent and Subagent Architecture"
            ]
          },
          {
            "sub_domain": "SNMP Transport and Communication",
            "atomic_topics": [
              "UDP as Default Transport Protocol",
              "TCP Transport Support",
              "Port 161 for Agent Requests",
              "Port 162 for Traps and Informs",
              "Port 10161 and 10162 Alternative Ports",
              "Transport Mapping Specifications",
              "Message Encoding and Transmission",
              "Connectionless Communication Model"
            ]
          }
        ]
      },
      {
        "domain": "SNMP Protocol Versions",
        "sub_domains": [
          {
            "sub_domain": "SNMPv1 (RFC 1157)",
            "atomic_topics": [
              "SNMPv1 Architecture and Goals",
              "Community-Based Security Model",
              "Plain Text Community Strings",
              "Read-Only (RO) Community Access",
              "Read-Write (RW) Community Access",
              "32-Bit Counter Support",
              "GetRequest PDU",
              "GetNextRequest PDU",
              "SetRequest PDU",
              "GetResponse PDU",
              "Trap PDU",
              "SNMPv1 Limitations and Security Issues"
            ]
          },
          {
            "sub_domain": "SNMPv2c (Community-Based SNMPv2)",
            "atomic_topics": [
              "SNMPv2c Enhancements over v1",
              "GetBulkRequest Operation",
              "InformRequest Operation",
              "SNMPv2 Trap Format",
              "64-Bit Counter Support",
              "Improved Error Handling",
              "Enhanced SET Command",
              "Community String Authentication",
              "Backward Compatibility with v1",
              "Performance Improvements"
            ]
          },
          {
            "sub_domain": "SNMPv3 (RFC 3411-3418)",
            "atomic_topics": [
              "SNMPv3 Security Architecture",
              "User-Based Security Model (USM)",
              "View-Based Access Control Model (VACM)",
              "Message Processing Models (v1MP, v2cMP, v3MP)",
              "Security Levels: noAuthNoPriv",
              "Security Levels: authNoPriv",
              "Security Levels: authPriv",
              "Authentication Protocols (MD5, SHA)",
              "Authentication Protocols (SHA-224, SHA-256, SHA-384, SHA-512)",
              "Encryption Protocols (DES, 3DES)",
              "Encryption Protocols (AES-128, AES-192, AES-256)",
              "snmpEngineID Unique Identifier",
              "snmpEngineBoots and snmpEngineTime",
              "Principal and securityName Concepts",
              "Remote Configuration Capabilities",
              "Context-Based Access Control"
            ]
          }
        ]
      },
      {
        "domain": "SNMP Operations and Protocol Data Units (PDUs)",
        "sub_domains": [
          {
            "sub_domain": "Request Operations",
            "atomic_topics": [
              "GET Operation for Single Value Retrieval",
              "GETNEXT Operation for MIB Traversal",
              "GETBULK Operation for Bulk Retrieval",
              "SET Operation for Value Modification",
              "Variable Bindings (VarBind) Structure",
              "Atomic SET Operations",
              "Lexicographical Ordering in GETNEXT",
              "MaxRepetitions Parameter in GETBULK",
              "NonRepeaters Parameter in GETBULK"
            ]
          },
          {
            "sub_domain": "Response Operations",
            "atomic_topics": [
              "GetResponse PDU Structure",
              "Response PDU in SNMPv2/v3",
              "Error Status Codes (noError, tooBig, noSuchName)",
              "Error Status Codes (badValue, readOnly, genErr)",
              "Error Index Field",
              "Response Timeout Handling",
              "Retry Mechanisms",
              "State Reference for Request Correlation"
            ]
          },
          {
            "sub_domain": "Notification Operations",
            "atomic_topics": [
              "TRAP Operation (Unacknowledged)",
              "INFORM Operation (Acknowledged)",
              "Generic Trap Types (coldStart, warmStart)",
              "Generic Trap Types (linkDown, linkUp)",
              "Generic Trap Types (authenticationFailure)",
              "Generic Trap Types (egpNeighborLoss)",
              "Enterprise-Specific Traps",
              "Trap PDU vs Trapv2 PDU",
              "Notification Originators and Receivers",
              "Trap Filtering and Rate Limiting"
            ]
          },
          {
            "sub_domain": "Polling Mechanisms",
            "atomic_topics": [
              "Periodic Polling Strategy",
              "Polling Intervals Configuration",
              "Polling Frequency Optimization",
              "Dynamic Polling Adjustments",
              "Polling vs Event-Driven Monitoring",
              "Threshold-Based Polling",
              "Intelligent Polling Strategies"
            ]
          }
        ]
      },
      {
        "domain": "Management Information Base (MIB)",
        "sub_domains": [
          {
            "sub_domain": "MIB Structure and Organization",
            "atomic_topics": [
              "Hierarchical Tree Structure",
              "MIB Database Concept",
              "Root Node Organization",
              "ISO Registration Hierarchy",
              "ORG and DOD Nodes",
              "Internet Node (1.3.6.1)",
              "Directory, Management, Experimental, Private Branches",
              "Enterprises Branch (1.3.6.1.4.1)",
              "MIB-II Standard Objects",
              "Vendor-Specific MIB Extensions"
            ]
          },
          {
            "sub_domain": "Object Identifiers (OIDs)",
            "atomic_topics": [
              "OID Notation and Syntax",
              "Dotted Decimal Notation",
              "Numeric vs Textual OID Representation",
              "OID Hierarchy and Inheritance",
              "Scalar Object Instances (x.0)",
              "Columnar Object Instances (Table Indexing)",
              "OID Translation and Resolution",
              "OID Uniqueness and Registration",
              "Private Enterprise Numbers (PEN)"
            ]
          },
          {
            "sub_domain": "MIB-II Standard Groups (RFC 1213)",
            "atomic_topics": [
              "System Group (sysDescr, sysUpTime, sysContact)",
              "Interfaces Group (ifTable, ifIndex, ifDescr)",
              "Address Translation (AT) Group",
              "IP Group (ipForwarding, ipInReceives, ipRoutingTable)",
              "ICMP Group (icmpInMsgs, icmpOutMsgs)",
              "TCP Group (tcpConnTable, tcpActiveOpens)",
              "UDP Group (udpInDatagrams, udpOutDatagrams)",
              "EGP Group",
              "Transmission Group",
              "SNMP Group (snmpInPkts, snmpOutPkts)"
            ]
          },
          {
            "sub_domain": "Enterprise and Vendor MIBs",
            "atomic_topics": [
              "Cisco Enterprise MIBs",
              "Juniper Enterprise MIBs",
              "HP/Aruba Enterprise MIBs",
              "Dell Enterprise MIBs",
              "Vendor-Specific OID Trees",
              "Proprietary MIB Extensions",
              "Device-Specific Monitoring Objects",
              "Custom MIB Development"
            ]
          },
          {
            "sub_domain": "MIB Compilation and Management",
            "atomic_topics": [
              "MIB Compilation Process",
              "MIB File Formats (.mib, .my)",
              "MIB Browser Tools",
              "MIB Locator Services",
              "MIB Dependencies and Imports",
              "MIB Validation and Testing",
              "MIB Repository Management",
              "Online MIB Databases"
            ]
          }
        ]
      },
      {
        "domain": "Structure of Management Information (SMI)",
        "sub_domains": [
          {
            "sub_domain": "SMI Framework and Standards",
            "atomic_topics": [
              "SMI Definition and Purpose (RFC 1155)",
              "SMIv1 Specifications",
              "SMIv2 Specifications (RFC 2578-2580)",
              "SMI Data Type Definitions",
              "Object Type Macro",
              "Trap Type Macro",
              "Module Identity Macro",
              "Textual Conventions",
              "Conformance Statements"
            ]
          },
          {
            "sub_domain": "Abstract Syntax Notation One (ASN.1)",
            "atomic_topics": [
              "ASN.1 Overview and Purpose",
              "ASN.1 Data Type Definitions",
              "ASN.1 SEQUENCE and SEQUENCE OF",
              "ASN.1 INTEGER Type",
              "ASN.1 OCTET STRING Type",
              "ASN.1 OBJECT IDENTIFIER Type",
              "ASN.1 NULL Type",
              "ASN.1 IpAddress Type",
              "ASN.1 Counter and Gauge Types",
              "ASN.1 TimeTicks Type",
              "ASN.1 Opaque Type"
            ]
          },
          {
            "sub_domain": "Basic Encoding Rules (BER)",
            "atomic_topics": [
              "BER Overview and Standards",
              "Tag-Length-Value (TLV) Encoding",
              "Primitive vs Constructor Encodings",
              "Definite-Length Encoding",
              "Indefinite-Length Encoding",
              "BER Encoding for INTEGER",
              "BER Encoding for OCTET STRING",
              "BER Encoding for OBJECT IDENTIFIER",
              "BER Encoding for SEQUENCE",
              "Distinguished Encoding Rules (DER)"
            ]
          }
        ]
      },
      {
        "domain": "SNMP Security",
        "sub_domains": [
          {
            "sub_domain": "Security Threats and Vulnerabilities",
            "atomic_topics": [
              "Principal Threats: Modification of Information",
              "Principal Threats: Masquerade",
              "Secondary Threats: Message Stream Modification",
              "Secondary Threats: Disclosure",
              "Eavesdropping and Packet Capture",
              "Replay Attacks",
              "Man-in-the-Middle Attacks",
              "Unauthorized Access",
              "Default Community String Exploitation",
              "SNMP Amplification DDoS Attacks"
            ]
          },
          {
            "sub_domain": "Authentication Mechanisms",
            "atomic_topics": [
              "Community String Authentication (v1/v2c)",
              "User-Based Authentication (v3)",
              "HMAC-MD5 Authentication",
              "HMAC-SHA Authentication Variants",
              "Authentication Key Generation",
              "Password Localization Process",
              "Time-Based Authentication",
              "Authentication Failure Traps",
              "Authentication Protocol Selection"
            ]
          },
          {
            "sub_domain": "Privacy and Encryption",
            "atomic_topics": [
              "Data Encryption Standard (DES)",
              "Triple DES (3DES) Encryption",
              "Advanced Encryption Standard (AES)",
              "AES Key Lengths (128, 192, 256 bits)",
              "Cipher Block Chaining (CBC) Mode",
              "Encryption Key Management",
              "Privacy Protocol Selection",
              "Payload Encryption Process"
            ]
          },
          {
            "sub_domain": "Access Control",
            "atomic_topics": [
              "View-Based Access Control Model (VACM)",
              "SNMP Views Definition",
              "SNMP Groups Configuration",
              "SNMP Users and Principals",
              "Read-Only Access Restrictions",
              "Read-Write Access Restrictions",
              "Context-Based Access Control",
              "MIB View Filtering",
              "Access Control Lists (ACLs)",
              "IP-Based Access Restrictions"
            ]
          },
          {
            "sub_domain": "Security Best Practices",
            "atomic_topics": [
              "SNMPv3 Adoption and Migration",
              "Strong Community String Generation",
              "Community String Length Requirements (20+ characters)",
              "Disabling Default Community Strings (public, private)",
              "Network Segmentation for SNMP Traffic",
              "Firewall Rules for Ports 161/162",
              "SNMP Traffic Encryption",
              "Regular Security Audits",
              "SNMP Credential Rotation",
              "Monitoring SNMP Access Logs",
              "Disabling Unnecessary SNMP Write Access"
            ]
          }
        ]
      },
      {
        "domain": "SNMP Implementation and Configuration",
        "sub_domains": [
          {
            "sub_domain": "SNMP Agent Configuration",
            "atomic_topics": [
              "Enabling SNMP Service on Devices",
              "Configuring Community Strings",
              "Setting System Information (sysLocation, sysContact)",
              "Defining SNMP Views",
              "Creating SNMP Groups",
              "Adding SNMP Users",
              "Configuring Trap Destinations",
              "Inform Receiver Configuration",
              "Agent Address Binding",
              "Agent Port Configuration"
            ]
          },
          {
            "sub_domain": "Cisco SNMP Configuration",
            "atomic_topics": [
              "snmp-server community Command",
              "snmp-server host Command",
              "snmp-server enable traps Command",
              "snmp-server view Command",
              "snmp-server group Command",
              "snmp-server user Command",
              "snmp-server engineID Command",
              "snmp-server location Command",
              "snmp-server contact Command",
              "Access List Integration with SNMP"
            ]
          },
          {
            "sub_domain": "Juniper SNMP Configuration",
            "atomic_topics": [
              "Junos SNMP Configuration Hierarchy",
              "Community Configuration in Junos",
              "Trap Group Configuration",
              "SNMP Views in Junos",
              "SNMPv3 Configuration in Junos",
              "Filter-Based SNMP Access Control",
              "SNMP MIB Support in Junos"
            ]
          },
          {
            "sub_domain": "Linux/Unix SNMP Configuration",
            "atomic_topics": [
              "Net-SNMP Installation",
              "snmpd.conf Configuration File",
              "snmptrapd.conf Configuration",
              "Community Configuration in Linux",
              "SNMPv3 User Setup in Linux",
              "View and Access Control in Net-SNMP",
              "SNMP Service Management (systemctl/service)",
              "Firewall Configuration for SNMP (iptables/firewalld)"
            ]
          },
          {
            "sub_domain": "Windows SNMP Configuration",
            "atomic_topics": [
              "Windows SNMP Service Installation",
              "SNMP Service Properties Configuration",
              "Community Configuration in Windows",
              "Trap Configuration in Windows",
              "Security Settings for SNMP Service",
              "Accepted Community Names",
              "SNMP Permissions in Windows",
              "Windows Firewall Rules for SNMP"
            ]
          }
        ]
      },
      {
        "domain": "SNMP Monitoring and Management",
        "sub_domains": [
          {
            "sub_domain": "Network Management Systems (NMS)",
            "atomic_topics": [
              "NMS Architecture and Components",
              "Centralized vs Distributed NMS",
              "NMS Database and Data Storage",
              "NMS User Interface and Dashboards",
              "Real-Time Monitoring Capabilities",
              "Historical Data Analysis",
              "Alert and Notification Systems",
              "Report Generation and Customization"
            ]
          },
          {
            "sub_domain": "SNMP Monitoring Tools",
            "atomic_topics": [
              "SolarWinds Network Performance Monitor",
              "PRTG Network Monitor",
              "Nagios and Nagios XI",
              "Zabbix SNMP Monitoring",
              "LibreNMS Open Source Platform",
              "Observium Network Monitoring",
              "Cacti Graphing Tool",
              "WhatsUp Gold",
              "ManageEngine OpManager",
              "Paessler SNMP Tools",
              "Datadog Infrastructure Monitoring",
              "LogicMonitor Platform"
            ]
          },
          {
            "sub_domain": "Monitored Metrics and Objects",
            "atomic_topics": [
              "Device Uptime Monitoring",
              "CPU Utilization Tracking",
              "Memory Usage Monitoring",
              "Disk Space and Storage Monitoring",
              "Interface Status and Statistics",
              "Bandwidth Utilization",
              "Packet Loss and Error Rates",
              "Temperature Sensors",
              "Power Supply Status",
              "Fan Speed Monitoring",
              "UPS Battery Status",
              "Printer Status (Toner, Paper Jams)",
              "NAS Device Health (RAID Status)"
            ]
          },
          {
            "sub_domain": "Alerting and Thresholds",
            "atomic_topics": [
              "Threshold Configuration",
              "Static vs Dynamic Thresholds",
              "Alert Severity Levels",
              "Email Notification Configuration",
              "SMS/Text Message Alerts",
              "Webhook Integration",
              "Alert Escalation Policies",
              "Alert Suppression and Filtering",
              "Alert Correlation",
              "Maintenance Windows"
            ]
          },
          {
            "sub_domain": "Performance and Capacity Planning",
            "atomic_topics": [
              "Trend Analysis and Forecasting",
              "Capacity Planning Metrics",
              "Baseline Establishment",
              "Peak Usage Identification",
              "Resource Utilization Reports",
              "Growth Projection Analysis",
              "Performance Bottleneck Identification",
              "SLA Compliance Monitoring"
            ]
          }
        ]
      },
      {
        "domain": "SNMP Advanced Topics",
        "sub_domains": [
          {
            "sub_domain": "SNMP Proxy and Gateway",
            "atomic_topics": [
              "SNMP Proxy Agent Functionality",
              "Proxy Forwarding Application",
              "Protocol Conversion via Proxy",
              "Subagent Architecture",
              "Master Agent and Subagent Communication",
              "AgentX Protocol (RFC 2741)",
              "SMUX Protocol",
              "Remote Network Monitoring via Proxy",
              "Proxy Access Policies"
            ]
          },
          {
            "sub_domain": "SNMP over Various Transports",
            "atomic_topics": [
              "SNMP over UDP/IPv4",
              "SNMP over UDP/IPv6",
              "SNMP over TCP",
              "SNMP over IEEE 802 Networks",
              "SNMP over TLS",
              "SNMP over DTLS",
              "SNMP over SSH",
              "Transport Security Considerations"
            ]
          },
          {
            "sub_domain": "SNMP Table Management",
            "atomic_topics": [
              "Table Structure in MIBs",
              "Table Indexing Strategies",
              "Single vs Multi-Index Tables",
              "Table Row Creation and Deletion",
              "RowStatus Object Usage",
              "Table Traversal Techniques",
              "Sparse Table Handling",
              "Large Table Performance Optimization"
            ]
          },
          {
            "sub_domain": "SNMP Context and Scoping",
            "atomic_topics": [
              "SNMP Context Definition",
              "contextEngineID",
              "contextName Usage",
              "scopedPDU Structure",
              "Multi-Context Environments",
              "Context-Based Isolation",
              "Virtual Router Context Monitoring"
            ]
          },
          {
            "sub_domain": "SNMP Message Size and Fragmentation",
            "atomic_topics": [
              "Maximum Message Size Constraints",
              "MTU Considerations",
              "Message Fragmentation Issues",
              "maxSizeResponseScopedPDU",
              "Handling tooBig Errors",
              "GETBULK Size Optimization",
              "Large Response Mitigation"
            ]
          }
        ]
      },
      {
        "domain": "SNMP Troubleshooting and Diagnostics",
        "sub_domains": [
          {
            "sub_domain": "SNMP Command-Line Tools",
            "atomic_topics": [
              "snmpget Utility",
              "snmpgetnext Utility",
              "snmpwalk Utility",
              "snmpbulkwalk Utility",
              "snmpset Utility",
              "snmptrap Utility",
              "snmpinform Utility",
              "snmptranslate Utility",
              "snmpstatus Utility",
              "snmptable Utility"
            ]
          },
          {
            "sub_domain": "Common SNMP Issues",
            "atomic_topics": [
              "Timeout Errors and Resolution",
              "No Response from Agent",
              "Incorrect Community String",
              "Authentication Failure",
              "Encryption/Decryption Errors",
              "MIB Loading Errors",
              "OID Not Found Errors",
              "Permission Denied Errors",
              "UDP Packet Loss",
              "Firewall Blocking SNMP Traffic"
            ]
          },
          {
            "sub_domain": "SNMP Debugging Techniques",
            "atomic_topics": [
              "Enabling SNMP Debug Mode",
              "Packet Capture with tcpdump/Wireshark",
              "Analyzing SNMP Packets",
              "SNMP Log File Analysis",
              "Testing SNMP Connectivity",
              "Verifying SNMP Configuration",
              "MIB Walk for Validation",
              "SNMP Test Tools (SNMP Tester)"
            ]
          },
          {
            "sub_domain": "SNMP Performance Troubleshooting",
            "atomic_topics": [
              "High CPU Usage from SNMP",
              "Agent Response Time Issues",
              "Polling Storm Detection",
              "Rate Limiting Configuration",
              "Query Optimization",
              "Reducing GETNEXT Operations",
              "Optimizing Polling Intervals",
              "Load Balancing SNMP Traffic"
            ]
          },
          {
            "sub_domain": "SNMP Verification Commands",
            "atomic_topics": [
              "show snmp Command (Cisco)",
              "show snmp mib Command",
              "show snmp engineID Command",
              "show snmp user Command",
              "show snmp group Command",
              "show snmp host Command",
              "show snmp community Command",
              "SNMP Service Status Verification"
            ]
          }
        ]
      },
      {
        "domain": "SNMP Integration and Automation",
        "sub_domains": [
          {
            "sub_domain": "SNMP API and Libraries",
            "atomic_topics": [
              "Net-SNMP C Library",
              "PySNMP Python Library",
              "SNMP4J Java Library",
              "PHP SNMP Extension",
              "PowerShell SNMP Cmdlets",
              "Go SNMP Libraries",
              "Ruby SNMP Libraries",
              "RESTful SNMP Gateways"
            ]
          },
          {
            "sub_domain": "Network Automation with SNMP",
            "atomic_topics": [
              "Automated Device Discovery",
              "Configuration Backup via SNMP",
              "Mass Configuration Changes",
              "Automated Threshold Adjustment",
              "Self-Healing Network Scripts",
              "Integration with Ansible",
              "Integration with Python Network Automation",
              "SNMP in CI/CD Pipelines"
            ]
          },
          {
            "sub_domain": "SNMP Integration with Other Protocols",
            "atomic_topics": [
              "SNMP to Syslog Conversion",
              "SNMP with NetFlow/IPFIX",
              "SNMP and RMON Integration",
              "SNMP with REST APIs",
              "SNMP to YANG Model Mapping",
              "SNMP and gRPC Coexistence",
              "Hybrid Monitoring Approaches"
            ]
          },
          {
            "sub_domain": "SNMP Data Export and Visualization",
            "atomic_topics": [
              "Exporting SNMP Data to Databases",
              "Time-Series Database Integration (InfluxDB, Prometheus)",
              "Grafana Visualization of SNMP Data",
              "Kibana and Elasticsearch Integration",
              "CSV Export from SNMP Data",
              "Custom Dashboard Creation",
              "Real-Time Graphing Solutions"
            ]
          }
        ]
      },
      {
        "domain": "SNMP in Specific Network Environments",
        "sub_domains": [
          {
            "sub_domain": "SNMP in Enterprise Networks",
            "atomic_topics": [
              "Campus Network SNMP Monitoring",
              "Branch Office Monitoring",
              "WAN Link Monitoring",
              "LAN Switch Monitoring",
              "Core Router Monitoring",
              "Wireless Controller SNMP",
              "VoIP Gateway Monitoring"
            ]
          },
          {
            "sub_domain": "SNMP in Data Center",
            "atomic_topics": [
              "Server Hardware Monitoring via SNMP",
              "Storage Array SNMP Monitoring",
              "PDU (Power Distribution Unit) Monitoring",
              "Environmental Monitoring (Temperature, Humidity)",
              "Spine-Leaf Architecture Monitoring",
              "Virtualization Host SNMP",
              "Container Infrastructure Monitoring"
            ]
          },
          {
            "sub_domain": "SNMP in Service Provider Networks",
            "atomic_topics": [
              "ISP Network Monitoring",
              "MPLS Network SNMP",
              "BGP Monitoring via SNMP",
              "Carrier-Grade NAT Monitoring",
              "Metro Ethernet Monitoring",
              "Optical Network Monitoring",
              "Subscriber Management Monitoring"
            ]
          },
          {
            "sub_domain": "SNMP in Cloud and SDN",
            "atomic_topics": [
              "Cloud Infrastructure SNMP Support",
              "Virtual Network Device Monitoring",
              "Software-Defined Networking SNMP",
              "SDN Controller SNMP Integration",
              "OpenFlow Switch Monitoring",
              "NFV (Network Functions Virtualization) Monitoring",
              "Multi-Tenant Environment Monitoring"
            ]
          },
          {
            "sub_domain": "SNMP in IoT and Industrial Networks",
            "atomic_topics": [
              "IoT Device SNMP Support",
              "Industrial Control System (ICS) Monitoring",
              "SCADA Network SNMP",
              "Building Management System SNMP",
              "Smart Grid Monitoring",
              "Resource-Constrained Device SNMP",
              "Edge Computing Device Monitoring"
            ]
          }
        ]
      },
      {
        "domain": "SNMP Standards and RFCs",
        "sub_domains": [
          {
            "sub_domain": "Core SNMP RFCs",
            "atomic_topics": [
              "RFC 1155 - Structure of Management Information (SMIv1)",
              "RFC 1157 - SNMPv1 Protocol",
              "RFC 1213 - MIB-II",
              "RFC 2578 - SMIv2 Structure",
              "RFC 2579 - SMIv2 Textual Conventions",
              "RFC 2580 - SMIv2 Conformance Statements",
              "RFC 3411 - SNMP Management Framework",
              "RFC 3412 - Message Processing and Dispatching",
              "RFC 3413 - SNMP Applications",
              "RFC 3414 - User-Based Security Model (USM)",
              "RFC 3415 - View-Based Access Control Model (VACM)",
              "RFC 3416 - Protocol Operations v2",
              "RFC 3417 - Transport Mappings",
              "RFC 3418 - MIB for SNMPv3"
            ]
          },
          {
            "sub_domain": "Extended SNMP RFCs",
            "atomic_topics": [
              "RFC 2741 - AgentX Protocol",
              "RFC 3826 - AES Encryption in SNMP",
              "RFC 4789 - SNMP over IEEE 802",
              "RFC 5343 - Context Engine ID Discovery",
              "RFC 5590 - Transport Subsystem",
              "RFC 5591 - TLS Transport Model",
              "RFC 5592 - SSH Transport Model",
              "RFC 6353 - Transport Layer Security (TLS) Transport",
              "RFC 7630 - HMAC-SHA-2 Authentication"
            ]
          },
          {
            "sub_domain": "Related Standards",
            "atomic_topics": [
              "IEEE 802.1AB - LLDP MIB",
              "IEEE 802.1Q - VLAN MIB",
              "IEEE 802.3 - Ethernet MIB",
              "ITU-T M.3010 - TMN Principles",
              "ISO/IEC Object Identifier Registration",
              "IANA Enterprise Numbers"
            ]
          }
        ]
      },
      {
        "domain": "SNMP Performance Optimization",
        "sub_domains": [
          {
            "sub_domain": "Agent-Side Optimization",
            "atomic_topics": [
              "Limiting SNMP Views",
              "Disabling Unused MIB Modules",
              "Caching Frequently Accessed Data",
              "Asynchronous Data Collection",
              "Rate Limiting SNMP Requests",
              "CPU Priority for SNMP Process",
              "Memory Allocation for SNMP"
            ]
          },
          {
            "sub_domain": "Manager-Side Optimization",
            "atomic_topics": [
              "Optimizing Polling Frequency",
              "Using GETBULK Instead of Multiple GETs",
              "Parallel vs Sequential Polling",
              "Connection Pooling",
              "Query Result Caching",
              "Adaptive Polling Strategies",
              "Distributed Polling Architecture"
            ]
          },
          {
            "sub_domain": "Network-Side Optimization",
            "atomic_topics": [
              "QoS for SNMP Traffic",
              "SNMP Traffic Prioritization",
              "Reducing UDP Packet Loss",
              "SNMP over Dedicated Management Network",
              "Out-of-Band Management",
              "Multicast for SNMP Notifications",
              "Bandwidth Allocation for SNMP"
            ]
          }
        ]
      },
      {
        "domain": "SNMP Migration and Coexistence",
        "sub_domains": [
          {
            "sub_domain": "Version Migration Strategies",
            "atomic_topics": [
              "SNMPv1 to SNMPv2c Migration",
              "SNMPv2c to SNMPv3 Migration",
              "Backward Compatibility Considerations",
              "Dual-Stack SNMP Configuration",
              "Migration Planning and Testing",
              "Phased Migration Approach",
              "Rollback Procedures"
            ]
          },
          {
            "sub_domain": "Protocol Coexistence",
            "atomic_topics": [
              "Running Multiple SNMP Versions Simultaneously",
              "Version-Specific Community Strings",
              "Version-Specific User Accounts",
              "Proxy-Based Version Translation",
              "Gateway Solutions for Mixed Environments",
              "NMS Support for Multiple Versions"
            ]
          },
          {
            "sub_domain": "Alternative Protocol Migration",
            "atomic_topics": [
              "SNMP to NETCONF Migration",
              "SNMP to RESTful API Migration",
              "SNMP to gRPC/gNMI Migration",
              "SNMP to Telemetry Streaming",
              "Hybrid Monitoring Architectures",
              "Gradual Protocol Transition Strategies"
            ]
          }
        ]
      }
    ]
  },
  "metadata": {
    "duration_seconds": 1736.926349,
    "timestamp": "2025-12-29T13:33:44.572611"
  }
}