{
  "domain_title": "edge-computing-and-fog-computing",
  "category_title": "specialized-domains-and-emerging-technologies",
  "curriculum_type": "software-engineering",
  "subdomain_count": 2,
  "aggregated_at": "2025-12-29T16:15:56.194183",
  "subdomains": [
    {
      "subdomain_title": "Edge Computing Concepts",
      "processed_at": "2025-12-29T16:09:07.329284",
      "result": {
        "subdomain_title": "Edge Computing Concepts",
        "curriculum_type": "software-engineering",
        "topic_root": "Edge Computing Concepts",
        "topic_root_citation": "https://aws.amazon.com/what-is/edge-computing/",
        "detailed_hierarchy": [
          {
            "level": 1,
            "domain": "Edge Computing Fundamentals",
            "subdomains": [
              {
                "level": 2,
                "subdomain": "Core Concepts and Definitions",
                "topics": [
                  {
                    "level": 3,
                    "topic": "Edge Computing Paradigm"
                  },
                  {
                    "level": 3,
                    "topic": "Distributed Computing Patterns"
                  },
                  {
                    "level": 3,
                    "topic": "Edge vs. Cloud vs. Fog Computing"
                  },
                  {
                    "level": 3,
                    "topic": "Decentralized Data Processing"
                  },
                  {
                    "level": 3,
                    "topic": "Real-Time Computing Requirements"
                  },
                  {
                    "level": 3,
                    "topic": "Latency Reduction Principles"
                  }
                ]
              },
              {
                "level": 2,
                "subdomain": "Edge Computing Architecture",
                "topics": [
                  {
                    "level": 3,
                    "topic": "Three-Tier Architecture (Edge-Fog-Cloud)"
                  },
                  {
                    "level": 3,
                    "topic": "Edge Devices Layer"
                  },
                  {
                    "level": 3,
                    "topic": "Edge Gateway Architecture"
                  },
                  {
                    "level": 3,
                    "topic": "Edge Server Infrastructure"
                  },
                  {
                    "level": 3,
                    "topic": "Network Layer Components"
                  },
                  {
                    "level": 3,
                    "topic": "Cloud Integration Layer"
                  }
                ]
              },
              {
                "level": 2,
                "subdomain": "Reference Architectures and Standards",
                "topics": [
                  {
                    "level": 3,
                    "topic": "IEEE 1934 OpenFog Reference Architecture"
                  },
                  {
                    "level": 3,
                    "topic": "IEEE 1935 Edge-Fog Systems Framework"
                  },
                  {
                    "level": 3,
                    "topic": "ETSI Multi-Access Edge Computing (MEC)"
                  },
                  {
                    "level": 3,
                    "topic": "Industrial Edge Computing Standards"
                  },
                  {
                    "level": 3,
                    "topic": "Edge Computing Interoperability"
                  },
                  {
                    "level": 3,
                    "topic": "Architectural Decision Records (ADR)"
                  }
                ]
              }
            ]
          },
          {
            "level": 1,
            "domain": "Edge Hardware and Infrastructure",
            "subdomains": [
              {
                "level": 2,
                "subdomain": "Edge Devices and Sensors",
                "topics": [
                  {
                    "level": 3,
                    "topic": "IoT Sensors and Actuators"
                  },
                  {
                    "level": 3,
                    "topic": "Smart Cameras and Video Devices"
                  },
                  {
                    "level": 3,
                    "topic": "Environmental Sensors"
                  },
                  {
                    "level": 3,
                    "topic": "Industrial Sensors and Controllers"
                  },
                  {
                    "level": 3,
                    "topic": "Wearable and Medical Devices"
                  },
                  {
                    "level": 3,
                    "topic": "Embedded Systems Hardware"
                  }
                ]
              },
              {
                "level": 2,
                "subdomain": "Computing Platforms",
                "topics": [
                  {
                    "level": 3,
                    "topic": "ARM Cortex-A Processors"
                  },
                  {
                    "level": 3,
                    "topic": "System-on-Chip (SoC) Architectures"
                  },
                  {
                    "level": 3,
                    "topic": "FPGA-Based Edge Computing"
                  },
                  {
                    "level": 3,
                    "topic": "GPU Edge Computing"
                  },
                  {
                    "level": 3,
                    "topic": "Microcontroller Platforms"
                  },
                  {
                    "level": 3,
                    "topic": "Edge Server Hardware"
                  }
                ]
              },
              {
                "level": 2,
                "subdomain": "Edge Data Centers",
                "topics": [
                  {
                    "level": 3,
                    "topic": "Micro Data Center Design"
                  },
                  {
                    "level": 3,
                    "topic": "Regional Edge Infrastructure"
                  },
                  {
                    "level": 3,
                    "topic": "Co-location Edge Facilities"
                  },
                  {
                    "level": 3,
                    "topic": "Rugged Edge Deployments"
                  },
                  {
                    "level": 3,
                    "topic": "Disconnected Edge Operations"
                  },
                  {
                    "level": 3,
                    "topic": "Edge Infrastructure Management"
                  }
                ]
              }
            ]
          },
          {
            "level": 1,
            "domain": "Edge Networking and Connectivity",
            "subdomains": [
              {
                "level": 2,
                "subdomain": "Network Technologies",
                "topics": [
                  {
                    "level": 3,
                    "topic": "5G Network Integration"
                  },
                  {
                    "level": 3,
                    "topic": "Mobile Edge Computing (MEC)"
                  },
                  {
                    "level": 3,
                    "topic": "Wi-Fi and Local Area Networks"
                  },
                  {
                    "level": 3,
                    "topic": "Bluetooth Low Energy (BLE)"
                  },
                  {
                    "level": 3,
                    "topic": "Satellite Connectivity"
                  },
                  {
                    "level": 3,
                    "topic": "Software-Defined Networking (SDN)"
                  }
                ]
              },
              {
                "level": 2,
                "subdomain": "Network Performance",
                "topics": [
                  {
                    "level": 3,
                    "topic": "Ultra-Low Latency Optimization"
                  },
                  {
                    "level": 3,
                    "topic": "Bandwidth Management"
                  },
                  {
                    "level": 3,
                    "topic": "Network Congestion Mitigation"
                  },
                  {
                    "level": 3,
                    "topic": "Quality of Service (QoS)"
                  },
                  {
                    "level": 3,
                    "topic": "Edge-to-Cloud Synchronization"
                  },
                  {
                    "level": 3,
                    "topic": "Network Resilience and Failover"
                  }
                ]
              },
              {
                "level": 2,
                "subdomain": "Communication Protocols",
                "topics": [
                  {
                    "level": 3,
                    "topic": "MQTT Protocol"
                  },
                  {
                    "level": 3,
                    "topic": "CoAP (Constrained Application Protocol)"
                  },
                  {
                    "level": 3,
                    "topic": "HTTP/REST APIs"
                  },
                  {
                    "level": 3,
                    "topic": "gRPC for Edge"
                  },
                  {
                    "level": 3,
                    "topic": "WebSocket Communication"
                  },
                  {
                    "level": 3,
                    "topic": "Edge-to-Edge Communication"
                  }
                ]
              }
            ]
          },
          {
            "level": 1,
            "domain": "Edge Software and Platforms",
            "subdomains": [
              {
                "level": 2,
                "subdomain": "Operating Systems and Runtime",
                "topics": [
                  {
                    "level": 3,
                    "topic": "Linux for Edge Devices"
                  },
                  {
                    "level": 3,
                    "topic": "Real-Time Operating Systems (RTOS)"
                  },
                  {
                    "level": 3,
                    "topic": "Embedded Linux Distributions"
                  },
                  {
                    "level": 3,
                    "topic": "Edge OS Optimization"
                  },
                  {
                    "level": 3,
                    "topic": "Lightweight OS Footprint"
                  },
                  {
                    "level": 3,
                    "topic": "Device Driver Management"
                  }
                ]
              },
              {
                "level": 2,
                "subdomain": "Containerization and Orchestration",
                "topics": [
                  {
                    "level": 3,
                    "topic": "Docker Containers at Edge"
                  },
                  {
                    "level": 3,
                    "topic": "Kubernetes for Edge (K3s, K0s)"
                  },
                  {
                    "level": 3,
                    "topic": "KubeEdge Platform"
                  },
                  {
                    "level": 3,
                    "topic": "Container Orchestration Strategies"
                  },
                  {
                    "level": 3,
                    "topic": "Microservices Architecture"
                  },
                  {
                    "level": 3,
                    "topic": "Edge Workload Management"
                  }
                ]
              },
              {
                "level": 2,
                "subdomain": "Edge Computing Platforms",
                "topics": [
                  {
                    "level": 3,
                    "topic": "AWS IoT Greengrass"
                  },
                  {
                    "level": 3,
                    "topic": "Azure IoT Edge"
                  },
                  {
                    "level": 3,
                    "topic": "AWS Outposts"
                  },
                  {
                    "level": 3,
                    "topic": "Azure Stack Edge"
                  },
                  {
                    "level": 3,
                    "topic": "Red Hat OpenShift at Edge"
                  },
                  {
                    "level": 3,
                    "topic": "Amazon EKS Anywhere"
                  }
                ]
              }
            ]
          },
          {
            "level": 1,
            "domain": "Edge Data Management",
            "subdomains": [
              {
                "level": 2,
                "subdomain": "Data Collection and Ingestion",
                "topics": [
                  {
                    "level": 3,
                    "topic": "Sensor Data Acquisition"
                  },
                  {
                    "level": 3,
                    "topic": "Streaming Data Ingestion"
                  },
                  {
                    "level": 3,
                    "topic": "Time-Series Data Collection"
                  },
                  {
                    "level": 3,
                    "topic": "Image and Video Capture"
                  },
                  {
                    "level": 3,
                    "topic": "Data Sampling Strategies"
                  },
                  {
                    "level": 3,
                    "topic": "Data Quality and Validation"
                  }
                ]
              },
              {
                "level": 2,
                "subdomain": "Data Storage and Caching",
                "topics": [
                  {
                    "level": 3,
                    "topic": "Local Edge Storage"
                  },
                  {
                    "level": 3,
                    "topic": "Distributed Edge Databases"
                  },
                  {
                    "level": 3,
                    "topic": "Time-Series Databases"
                  },
                  {
                    "level": 3,
                    "topic": "Content Delivery Networks (CDN)"
                  },
                  {
                    "level": 3,
                    "topic": "Edge Caching Strategies"
                  },
                  {
                    "level": 3,
                    "topic": "AWS Storage Gateway"
                  }
                ]
              },
              {
                "level": 2,
                "subdomain": "Data Processing and Analytics",
                "topics": [
                  {
                    "level": 3,
                    "topic": "Real-Time Stream Processing"
                  },
                  {
                    "level": 3,
                    "topic": "Edge Data Filtering"
                  },
                  {
                    "level": 3,
                    "topic": "Data Aggregation Techniques"
                  },
                  {
                    "level": 3,
                    "topic": "Big Data Analytics at Edge"
                  },
                  {
                    "level": 3,
                    "topic": "Data Decimation and Reduction"
                  },
                  {
                    "level": 3,
                    "topic": "Edge ETL Pipelines"
                  }
                ]
              }
            ]
          },
          {
            "level": 1,
            "domain": "Edge AI and Machine Learning",
            "subdomains": [
              {
                "level": 2,
                "subdomain": "ML Model Deployment",
                "topics": [
                  {
                    "level": 3,
                    "topic": "Model Training vs. Inference"
                  },
                  {
                    "level": 3,
                    "topic": "Edge ML Model Optimization"
                  },
                  {
                    "level": 3,
                    "topic": "Model Quantization"
                  },
                  {
                    "level": 3,
                    "topic": "Model Compression Techniques"
                  },
                  {
                    "level": 3,
                    "topic": "TensorFlow Lite for Edge"
                  },
                  {
                    "level": 3,
                    "topic": "Amazon SageMaker Edge Manager"
                  }
                ]
              },
              {
                "level": 2,
                "subdomain": "Deep Learning at Edge",
                "topics": [
                  {
                    "level": 3,
                    "topic": "Neural Network Architecture Selection"
                  },
                  {
                    "level": 3,
                    "topic": "Convolutional Neural Networks (CNNs)"
                  },
                  {
                    "level": 3,
                    "topic": "Edge Computer Vision"
                  },
                  {
                    "level": 3,
                    "topic": "Object Detection and Recognition"
                  },
                  {
                    "level": 3,
                    "topic": "Image Classification at Edge"
                  },
                  {
                    "level": 3,
                    "topic": "Video Analytics Processing"
                  }
                ]
              },
              {
                "level": 2,
                "subdomain": "AI Frameworks and Hardware",
                "topics": [
                  {
                    "level": 3,
                    "topic": "GPU-Accelerated Edge AI"
                  },
                  {
                    "level": 3,
                    "topic": "Neural Processing Units (NPUs)"
                  },
                  {
                    "level": 3,
                    "topic": "AI Hardware Accelerators"
                  },
                  {
                    "level": 3,
                    "topic": "FPGA-Based AI Inference"
                  },
                  {
                    "level": 3,
                    "topic": "Edge AI PaaS Platforms"
                  },
                  {
                    "level": 3,
                    "topic": "Distributed AI Training"
                  }
                ]
              }
            ]
          },
          {
            "level": 1,
            "domain": "Edge Security and Privacy",
            "subdomains": [
              {
                "level": 2,
                "subdomain": "Authentication and Access Control",
                "topics": [
                  {
                    "level": 3,
                    "topic": "Device Authentication"
                  },
                  {
                    "level": 3,
                    "topic": "Multi-Factor Authentication (MFA)"
                  },
                  {
                    "level": 3,
                    "topic": "Password-Based Authentication"
                  },
                  {
                    "level": 3,
                    "topic": "Certificate-Based Authentication"
                  },
                  {
                    "level": 3,
                    "topic": "Role-Based Access Control (RBAC)"
                  },
                  {
                    "level": 3,
                    "topic": "Zero-Trust Networking"
                  }
                ]
              },
              {
                "level": 2,
                "subdomain": "Data Security",
                "topics": [
                  {
                    "level": 3,
                    "topic": "Data Encryption at Rest"
                  },
                  {
                    "level": 3,
                    "topic": "Data Encryption in Transit"
                  },
                  {
                    "level": 3,
                    "topic": "End-to-End Encryption"
                  },
                  {
                    "level": 3,
                    "topic": "Hardware Security Modules (HSM)"
                  },
                  {
                    "level": 3,
                    "topic": "Secure Boot and Firmware"
                  },
                  {
                    "level": 3,
                    "topic": "Cryptographic Key Management"
                  }
                ]
              },
              {
                "level": 2,
                "subdomain": "Privacy and Compliance",
                "topics": [
                  {
                    "level": 3,
                    "topic": "Data Sovereignty"
                  },
                  {
                    "level": 3,
                    "topic": "GDPR Compliance"
                  },
                  {
                    "level": 3,
                    "topic": "HIPAA Compliance"
                  },
                  {
                    "level": 3,
                    "topic": "Data Residency Requirements"
                  },
                  {
                    "level": 3,
                    "topic": "Privacy-Preserving Computation"
                  },
                  {
                    "level": 3,
                    "topic": "Secure Data Deletion"
                  }
                ]
              }
            ]
          },
          {
            "level": 1,
            "domain": "Edge Application Development",
            "subdomains": [
              {
                "level": 2,
                "subdomain": "Programming and Development",
                "topics": [
                  {
                    "level": 3,
                    "topic": "C/C++ for Embedded Edge"
                  },
                  {
                    "level": 3,
                    "topic": "Python for Edge Computing"
                  },
                  {
                    "level": 3,
                    "topic": "Go Language Applications"
                  },
                  {
                    "level": 3,
                    "topic": "Rust for Edge Systems"
                  },
                  {
                    "level": 3,
                    "topic": "JavaScript/Node.js at Edge"
                  },
                  {
                    "level": 3,
                    "topic": "Cross-Platform Development"
                  }
                ]
              },
              {
                "level": 2,
                "subdomain": "Application Architecture",
                "topics": [
                  {
                    "level": 3,
                    "topic": "Event-Driven Architecture"
                  },
                  {
                    "level": 3,
                    "topic": "Serverless Edge Functions"
                  },
                  {
                    "level": 3,
                    "topic": "Microservices Design Patterns"
                  },
                  {
                    "level": 3,
                    "topic": "Service Mesh for Edge"
                  },
                  {
                    "level": 3,
                    "topic": "API Gateway Design"
                  },
                  {
                    "level": 3,
                    "topic": "Edge Application Lifecycle"
                  }
                ]
              },
              {
                "level": 2,
                "subdomain": "Development Tools and Testing",
                "topics": [
                  {
                    "level": 3,
                    "topic": "Edge Device Emulation"
                  },
                  {
                    "level": 3,
                    "topic": "Simulation and Modeling"
                  },
                  {
                    "level": 3,
                    "topic": "Debugging Edge Applications"
                  },
                  {
                    "level": 3,
                    "topic": "Performance Profiling"
                  },
                  {
                    "level": 3,
                    "topic": "CI/CD for Edge"
                  },
                  {
                    "level": 3,
                    "topic": "Testing Strategies"
                  }
                ]
              }
            ]
          },
          {
            "level": 1,
            "domain": "Performance Optimization",
            "subdomains": [
              {
                "level": 2,
                "subdomain": "Computational Optimization",
                "topics": [
                  {
                    "level": 3,
                    "topic": "Computational Complexity Reduction"
                  },
                  {
                    "level": 3,
                    "topic": "Algorithm Optimization"
                  },
                  {
                    "level": 3,
                    "topic": "Parallel Processing at Edge"
                  },
                  {
                    "level": 3,
                    "topic": "Hardware Acceleration"
                  },
                  {
                    "level": 3,
                    "topic": "CPU vs. GPU vs. FPGA Trade-offs"
                  },
                  {
                    "level": 3,
                    "topic": "Workload Partitioning"
                  }
                ]
              },
              {
                "level": 2,
                "subdomain": "Resource Management",
                "topics": [
                  {
                    "level": 3,
                    "topic": "Memory Management"
                  },
                  {
                    "level": 3,
                    "topic": "Storage Optimization"
                  },
                  {
                    "level": 3,
                    "topic": "Compute Resource Allocation"
                  },
                  {
                    "level": 3,
                    "topic": "Dynamic Scaling Strategies"
                  },
                  {
                    "level": 3,
                    "topic": "Load Balancing"
                  },
                  {
                    "level": 3,
                    "topic": "Resource Monitoring"
                  }
                ]
              },
              {
                "level": 2,
                "subdomain": "Power and Energy Efficiency",
                "topics": [
                  {
                    "level": 3,
                    "topic": "Power Consumption Analysis"
                  },
                  {
                    "level": 3,
                    "topic": "Energy-Efficient Algorithms"
                  },
                  {
                    "level": 3,
                    "topic": "Dynamic Voltage Scaling"
                  },
                  {
                    "level": 3,
                    "topic": "Sleep Mode Management"
                  },
                  {
                    "level": 3,
                    "topic": "Battery-Powered Edge Devices"
                  },
                  {
                    "level": 3,
                    "topic": "Thermal Management"
                  }
                ]
              }
            ]
          },
          {
            "level": 1,
            "domain": "Edge Orchestration and Management",
            "subdomains": [
              {
                "level": 2,
                "subdomain": "Device Management",
                "topics": [
                  {
                    "level": 3,
                    "topic": "Device Provisioning"
                  },
                  {
                    "level": 3,
                    "topic": "Device Registration"
                  },
                  {
                    "level": 3,
                    "topic": "Remote Device Management"
                  },
                  {
                    "level": 3,
                    "topic": "Firmware Updates (OTA)"
                  },
                  {
                    "level": 3,
                    "topic": "Device Configuration Management"
                  },
                  {
                    "level": 3,
                    "topic": "Fleet Management"
                  }
                ]
              },
              {
                "level": 2,
                "subdomain": "Autonomic Management",
                "topics": [
                  {
                    "level": 3,
                    "topic": "Self-Configuration"
                  },
                  {
                    "level": 3,
                    "topic": "Self-Healing Systems"
                  },
                  {
                    "level": 3,
                    "topic": "Self-Optimization"
                  },
                  {
                    "level": 3,
                    "topic": "Self-Protection Mechanisms"
                  },
                  {
                    "level": 3,
                    "topic": "Automated Orchestration"
                  },
                  {
                    "level": 3,
                    "topic": "Policy-Based Management"
                  }
                ]
              },
              {
                "level": 2,
                "subdomain": "Monitoring and Observability",
                "topics": [
                  {
                    "level": 3,
                    "topic": "Metrics Collection"
                  },
                  {
                    "level": 3,
                    "topic": "Logging and Log Aggregation"
                  },
                  {
                    "level": 3,
                    "topic": "Distributed Tracing"
                  },
                  {
                    "level": 3,
                    "topic": "Prometheus for Edge"
                  },
                  {
                    "level": 3,
                    "topic": "Grafana Visualization"
                  },
                  {
                    "level": 3,
                    "topic": "Alerting and Notifications"
                  }
                ]
              }
            ]
          },
          {
            "level": 1,
            "domain": "IoT and Edge Integration",
            "subdomains": [
              {
                "level": 2,
                "subdomain": "IoT Protocols and Standards",
                "topics": [
                  {
                    "level": 3,
                    "topic": "OPC UA (Unified Architecture)"
                  },
                  {
                    "level": 3,
                    "topic": "Modbus Protocol"
                  },
                  {
                    "level": 3,
                    "topic": "Zigbee and Z-Wave"
                  },
                  {
                    "level": 3,
                    "topic": "LoRaWAN Integration"
                  },
                  {
                    "level": 3,
                    "topic": "Thread Protocol"
                  },
                  {
                    "level": 3,
                    "topic": "Matter (Smart Home Standard)"
                  }
                ]
              },
              {
                "level": 2,
                "subdomain": "Industrial IoT (IIoT)",
                "topics": [
                  {
                    "level": 3,
                    "topic": "Industrial Edge Computing"
                  },
                  {
                    "level": 3,
                    "topic": "Manufacturing Execution Systems (MES)"
                  },
                  {
                    "level": 3,
                    "topic": "Predictive Maintenance"
                  },
                  {
                    "level": 3,
                    "topic": "Digital Twins"
                  },
                  {
                    "level": 3,
                    "topic": "SCADA System Integration"
                  },
                  {
                    "level": 3,
                    "topic": "Robotics and Automation"
                  }
                ]
              },
              {
                "level": 2,
                "subdomain": "IoT Device Integration",
                "topics": [
                  {
                    "level": 3,
                    "topic": "Device-to-Cloud Communication"
                  },
                  {
                    "level": 3,
                    "topic": "Device-to-Device (D2D) Communication"
                  },
                  {
                    "level": 3,
                    "topic": "Machine-to-Machine (M2M)"
                  },
                  {
                    "level": 3,
                    "topic": "Gateway Integration Patterns"
                  },
                  {
                    "level": 3,
                    "topic": "Protocol Translation"
                  },
                  {
                    "level": 3,
                    "topic": "Legacy Device Integration"
                  }
                ]
              }
            ]
          },
          {
            "level": 1,
            "domain": "Edge Computing Design Trade-offs",
            "subdomains": [
              {
                "level": 2,
                "subdomain": "Performance vs. Cost",
                "topics": [
                  {
                    "level": 3,
                    "topic": "Bandwidth Cost Analysis"
                  },
                  {
                    "level": 3,
                    "topic": "Compute Cost Trade-offs"
                  },
                  {
                    "level": 3,
                    "topic": "Storage Cost Optimization"
                  },
                  {
                    "level": 3,
                    "topic": "Total Cost of Ownership (TCO)"
                  },
                  {
                    "level": 3,
                    "topic": "CAPEX vs. OPEX Models"
                  },
                  {
                    "level": 3,
                    "topic": "Cloud vs. Edge Economics"
                  }
                ]
              },
              {
                "level": 2,
                "subdomain": "Latency and Bandwidth",
                "topics": [
                  {
                    "level": 3,
                    "topic": "Latency Requirements Analysis"
                  },
                  {
                    "level": 3,
                    "topic": "Bandwidth Reduction Strategies"
                  },
                  {
                    "level": 3,
                    "topic": "Edge vs. Cloud Processing Decision"
                  },
                  {
                    "level": 3,
                    "topic": "Data Transmission Optimization"
                  },
                  {
                    "level": 3,
                    "topic": "Network Round-Trip Time (RTT)"
                  },
                  {
                    "level": 3,
                    "topic": "Offloading Strategies"
                  }
                ]
              },
              {
                "level": 2,
                "subdomain": "Precision and Accuracy",
                "topics": [
                  {
                    "level": 3,
                    "topic": "Floating-Point vs. Fixed-Point"
                  },
                  {
                    "level": 3,
                    "topic": "Numerical Precision Requirements"
                  },
                  {
                    "level": 3,
                    "topic": "Quantization Trade-offs"
                  },
                  {
                    "level": 3,
                    "topic": "Data Compression vs. Accuracy"
                  },
                  {
                    "level": 3,
                    "topic": "Approximation Algorithms"
                  },
                  {
                    "level": 3,
                    "topic": "Error Tolerance Analysis"
                  }
                ]
              }
            ]
          },
          {
            "level": 1,
            "domain": "Network Slicing and Virtualization",
            "subdomains": [
              {
                "level": 2,
                "subdomain": "5G Network Slicing",
                "topics": [
                  {
                    "level": 3,
                    "topic": "Network Slice Architecture"
                  },
                  {
                    "level": 3,
                    "topic": "Slice Isolation Mechanisms"
                  },
                  {
                    "level": 3,
                    "topic": "Dynamic Slice Management"
                  },
                  {
                    "level": 3,
                    "topic": "Quality of Service (QoS) per Slice"
                  },
                  {
                    "level": 3,
                    "topic": "Network Function Virtualization (NFV)"
                  },
                  {
                    "level": 3,
                    "topic": "Radio Access Network (RAN) Slicing"
                  }
                ]
              },
              {
                "level": 2,
                "subdomain": "Software-Defined Infrastructure",
                "topics": [
                  {
                    "level": 3,
                    "topic": "Software-Defined Clouds"
                  },
                  {
                    "level": 3,
                    "topic": "Virtual Network Functions (VNFs)"
                  },
                  {
                    "level": 3,
                    "topic": "OpenStack for Edge"
                  },
                  {
                    "level": 3,
                    "topic": "Network Virtualization"
                  },
                  {
                    "level": 3,
                    "topic": "Infrastructure Programmability"
                  },
                  {
                    "level": 3,
                    "topic": "SDN Controllers"
                  }
                ]
              },
              {
                "level": 2,
                "subdomain": "Resource Slicing",
                "topics": [
                  {
                    "level": 3,
                    "topic": "Compute Resource Slicing"
                  },
                  {
                    "level": 3,
                    "topic": "Storage Resource Slicing"
                  },
                  {
                    "level": 3,
                    "topic": "Network Resource Slicing"
                  },
                  {
                    "level": 3,
                    "topic": "GPU Partitioning"
                  },
                  {
                    "level": 3,
                    "topic": "Slice Orchestration"
                  },
                  {
                    "level": 3,
                    "topic": "Multi-Tenancy Support"
                  }
                ]
              }
            ]
          },
          {
            "level": 1,
            "domain": "Edge Computing Use Cases",
            "subdomains": [
              {
                "level": 2,
                "subdomain": "Smart Cities and Transportation",
                "topics": [
                  {
                    "level": 3,
                    "topic": "Traffic Management Systems"
                  },
                  {
                    "level": 3,
                    "topic": "Autonomous Vehicles"
                  },
                  {
                    "level": 3,
                    "topic": "Smart Parking Solutions"
                  },
                  {
                    "level": 3,
                    "topic": "Public Safety and Surveillance"
                  },
                  {
                    "level": 3,
                    "topic": "Environmental Monitoring"
                  },
                  {
                    "level": 3,
                    "topic": "Smart Street Lighting"
                  }
                ]
              },
              {
                "level": 2,
                "subdomain": "Healthcare and Medical",
                "topics": [
                  {
                    "level": 3,
                    "topic": "Remote Patient Monitoring"
                  },
                  {
                    "level": 3,
                    "topic": "Medical Device Edge Computing"
                  },
                  {
                    "level": 3,
                    "topic": "Real-Time Diagnostics"
                  },
                  {
                    "level": 3,
                    "topic": "Telemedicine Applications"
                  },
                  {
                    "level": 3,
                    "topic": "Healthcare Data Privacy"
                  },
                  {
                    "level": 3,
                    "topic": "Infusion Pump Management"
                  }
                ]
              },
              {
                "level": 2,
                "subdomain": "Retail and Entertainment",
                "topics": [
                  {
                    "level": 3,
                    "topic": "Retail Analytics"
                  },
                  {
                    "level": 3,
                    "topic": "Inventory Management"
                  },
                  {
                    "level": 3,
                    "topic": "Digital Signage"
                  },
                  {
                    "level": 3,
                    "topic": "Content Streaming and CDN"
                  },
                  {
                    "level": 3,
                    "topic": "Gaming Edge Servers"
                  },
                  {
                    "level": 3,
                    "topic": "Augmented Reality (AR) Applications"
                  }
                ]
              }
            ]
          },
          {
            "level": 1,
            "domain": "Emerging Edge Technologies",
            "subdomains": [
              {
                "level": 2,
                "subdomain": "Blockchain and Distributed Ledger",
                "topics": [
                  {
                    "level": 3,
                    "topic": "Blockchain-Based Orchestration"
                  },
                  {
                    "level": 3,
                    "topic": "Distributed Ledger Technology (DLT)"
                  },
                  {
                    "level": 3,
                    "topic": "Smart Contracts at Edge"
                  },
                  {
                    "level": 3,
                    "topic": "Decentralized Identity"
                  },
                  {
                    "level": 3,
                    "topic": "Cryptocurrency Mining at Edge"
                  },
                  {
                    "level": 3,
                    "topic": "Trust and Consensus Mechanisms"
                  }
                ]
              },
              {
                "level": 2,
                "subdomain": "Quantum and Sovereign Computing",
                "topics": [
                  {
                    "level": 3,
                    "topic": "Quantum Computing Integration"
                  },
                  {
                    "level": 3,
                    "topic": "Post-Quantum Cryptography"
                  },
                  {
                    "level": 3,
                    "topic": "Sovereign AI"
                  },
                  {
                    "level": 3,
                    "topic": "Sovereign Cloud Architecture"
                  },
                  {
                    "level": 3,
                    "topic": "Geopolitical Data Considerations"
                  },
                  {
                    "level": 3,
                    "topic": "National Security Requirements"
                  }
                ]
              },
              {
                "level": 2,
                "subdomain": "Advanced Connectivity",
                "topics": [
                  {
                    "level": 3,
                    "topic": "6G Vision for Edge"
                  },
                  {
                    "level": 3,
                    "topic": "Satellite Edge Computing"
                  },
                  {
                    "level": 3,
                    "topic": "Low Earth Orbit (LEO) Integration"
                  },
                  {
                    "level": 3,
                    "topic": "Drone-Based Edge Computing"
                  },
                  {
                    "level": 3,
                    "topic": "Vehicle-to-Everything (V2X)"
                  },
                  {
                    "level": 3,
                    "topic": "Edge-Native Applications"
                  }
                ]
              }
            ]
          }
        ]
      }
    },
    {
      "subdomain_title": "Edge Platforms",
      "processed_at": "2025-12-29T16:09:45.258413",
      "result": {
        "subdomain_title": "Edge Platforms",
        "curriculum_type": "software-engineering",
        "topic_root": "Edge Platforms",
        "topic_root_citation": "https://aws.amazon.com/edge/",
        "detailed_hierarchy": [
          {
            "domain": "Edge Infrastructure",
            "sub_domains": [
              {
                "sub_domain": "Edge Network Architecture",
                "topics": [
                  "Points of Presence (PoP)",
                  "Edge Data Centers",
                  "Content Delivery Networks (CDN)",
                  "Anycast Routing",
                  "Unicast Routing",
                  "Multi-Tier Cache Architecture",
                  "Origin Servers",
                  "Edge Nodes",
                  "Regional Edge Zones",
                  "Metro Area Infrastructure"
                ]
              },
              {
                "sub_domain": "Edge Hardware",
                "topics": [
                  "Edge Servers",
                  "IoT Gateways",
                  "Smart Sensors",
                  "Ruggedized Edge Devices",
                  "Portable Edge Appliances",
                  "Hardware-Accelerated ML Components",
                  "FPGA-based Edge Processing",
                  "GPU-accelerated Edge Devices",
                  "Edge Storage Appliances",
                  "Industrial Edge Controllers"
                ]
              },
              {
                "sub_domain": "Edge Device Management",
                "topics": [
                  "Device Provisioning",
                  "Device Activation",
                  "Fleet Management",
                  "Remote Device Configuration",
                  "Firmware Updates",
                  "Device Lifecycle Management",
                  "Edge Device Orchestration",
                  "Device Health Monitoring",
                  "Asset Tracking",
                  "Device Return and Decommissioning"
                ]
              },
              {
                "sub_domain": "Physical Deployment Models",
                "topics": [
                  "On-Premises Deployments",
                  "Co-Location Facilities",
                  "Remote Site Deployments",
                  "Disconnected Edge Environments",
                  "Mobile Edge Computing (MEC)",
                  "Austere Environment Deployments",
                  "Maritime Edge Deployments",
                  "Industrial Plant Deployments",
                  "Retail Edge Locations",
                  "Smart City Infrastructure"
                ]
              }
            ]
          },
          {
            "domain": "Edge Compute",
            "sub_domains": [
              {
                "sub_domain": "Serverless Edge Computing",
                "topics": [
                  "Edge Functions",
                  "Function as a Service (FaaS)",
                  "Serverless Workers",
                  "Lambda@Edge",
                  "Event-Driven Architecture",
                  "Request/Response Handling",
                  "Fetch API Standards",
                  "Cold Start Optimization",
                  "Auto-Scaling",
                  "Concurrency Management"
                ]
              },
              {
                "sub_domain": "Edge Runtime Environments",
                "topics": [
                  "V8 Isolates",
                  "WebAssembly (WASM)",
                  "JavaScript/TypeScript Runtime",
                  "Python Edge Runtime",
                  "Rust Edge Runtime",
                  "Edge Runtime Standards",
                  "Workerd Runtime",
                  "Container Runtime",
                  "Multi-Tenant Isolation",
                  "Sandbox Security"
                ]
              },
              {
                "sub_domain": "Edge Workload Orchestration",
                "topics": [
                  "Kubernetes at the Edge",
                  "K3s Lightweight Distribution",
                  "KubeEdge Platform",
                  "Container Orchestration",
                  "IoT Edge Modules",
                  "Stateless Application Deployment",
                  "Stateful Application Deployment",
                  "Workload Scheduling",
                  "Resource Allocation",
                  "Multi-Cluster Management"
                ]
              },
              {
                "sub_domain": "Edge Virtual Machines",
                "topics": [
                  "VM Deployment Models",
                  "Hypervisor at the Edge",
                  "VM Templates and Images",
                  "VM Lifecycle Management",
                  "Resource Virtualization",
                  "VM Migration",
                  "Snapshot Management",
                  "VM Networking",
                  "VM Storage Integration",
                  "Performance Optimization"
                ]
              },
              {
                "sub_domain": "Distributed Processing",
                "topics": [
                  "Local Data Processing",
                  "Real-Time Processing",
                  "Batch Processing at Edge",
                  "Stream Processing",
                  "Edge-to-Cloud Offloading",
                  "Task Offloading Strategies",
                  "Computation Relocation",
                  "Smart Placement Algorithms",
                  "Workload Distribution",
                  "Load Balancing"
                ]
              }
            ]
          },
          {
            "domain": "Edge Networking",
            "sub_domains": [
              {
                "sub_domain": "Network Protocols",
                "topics": [
                  "HTTP/1.1",
                  "HTTP/2",
                  "HTTP/3",
                  "QUIC Protocol",
                  "TCP Optimization",
                  "UDP-based Protocols",
                  "WebSocket Protocol",
                  "gRPC at the Edge",
                  "MQTT Protocol",
                  "CoAP Protocol"
                ]
              },
              {
                "sub_domain": "DNS and Routing",
                "topics": [
                  "Edge DNS Resolution",
                  "Anycast DNS",
                  "Recursive DNS Resolvers",
                  "Authoritative Nameservers",
                  "DNS Load Balancing",
                  "GeoDNS Routing",
                  "Smart Routing",
                  "BGP (Border Gateway Protocol)",
                  "IP Routing Optimization",
                  "Traffic Steering"
                ]
              },
              {
                "sub_domain": "Latency Optimization",
                "topics": [
                  "Round-Trip Time (RTT) Reduction",
                  "Network Hop Minimization",
                  "Connection Pooling",
                  "TCP Connection Reuse",
                  "Multiplexing",
                  "Early Hints",
                  "Prefetching Strategies",
                  "Keep-Alive Connections",
                  "Protocol Optimization",
                  "Geographic Proximity Routing"
                ]
              },
              {
                "sub_domain": "Bandwidth Management",
                "topics": [
                  "Compression (Gzip, Brotli)",
                  "Content Minification",
                  "Bandwidth Throttling",
                  "Traffic Shaping",
                  "Quality of Service (QoS)",
                  "Adaptive Bitrate Streaming",
                  "Image Optimization",
                  "Video Optimization",
                  "Delta Encoding",
                  "Deduplication"
                ]
              },
              {
                "sub_domain": "5G and Mobile Edge",
                "topics": [
                  "5G Network Integration",
                  "Multi-Access Edge Computing (MEC)",
                  "Ultra-Low Latency Services",
                  "Network Slicing",
                  "Mobile Backhaul",
                  "Radio Access Network (RAN)",
                  "Carrier-Grade Edge",
                  "Telecom Edge Infrastructure",
                  "Edge-Cloud Interconnection",
                  "Communication Service Provider (CSP) Integration"
                ]
              },
              {
                "sub_domain": "IoT Connectivity",
                "topics": [
                  "IoT Gateway Protocols",
                  "AMQP Protocol",
                  "Bluetooth/BLE",
                  "Zigbee Protocol",
                  "LoRaWAN",
                  "NFC Communication",
                  "WiFi at the Edge",
                  "Cellular IoT (NB-IoT, LTE-M)",
                  "Edge-to-Device Communication",
                  "Device-to-Device (D2D) Communication"
                ]
              }
            ]
          },
          {
            "domain": "Edge Storage and Data Management",
            "sub_domains": [
              {
                "sub_domain": "Edge Caching",
                "topics": [
                  "Cache Hit Ratio Optimization",
                  "Cache-Control Headers",
                  "Time-to-Live (TTL) Management",
                  "Cache Invalidation",
                  "Cache Purging",
                  "Cache Warming",
                  "Cache Revalidation",
                  "Stale-While-Revalidate",
                  "Edge-Side Includes (ESI)",
                  "Smart Tiered Caching"
                ]
              },
              {
                "sub_domain": "Edge Storage Systems",
                "topics": [
                  "Key-Value Stores",
                  "Object Storage at Edge",
                  "Edge Databases",
                  "Distributed File Systems",
                  "Block Storage",
                  "NFS/SMB Shares",
                  "Edge Storage Accounts",
                  "Persistent Storage",
                  "Ephemeral Storage",
                  "Storage Virtualization"
                ]
              },
              {
                "sub_domain": "Data Synchronization",
                "topics": [
                  "Edge-to-Cloud Sync",
                  "Bidirectional Replication",
                  "Conflict Resolution",
                  "Eventually Consistent Systems",
                  "Strong Consistency Models",
                  "Data Versioning",
                  "Change Data Capture (CDC)",
                  "Delta Synchronization",
                  "Offline Data Management",
                  "Data Reconciliation"
                ]
              },
              {
                "sub_domain": "Distributed Databases",
                "topics": [
                  "Edge SQL Databases",
                  "NoSQL at the Edge",
                  "Time-Series Databases",
                  "Graph Databases",
                  "In-Memory Databases",
                  "Database Sharding",
                  "Read Replicas",
                  "Database Connection Pooling",
                  "Query Optimization",
                  "Transaction Management"
                ]
              },
              {
                "sub_domain": "Data Transfer and Migration",
                "topics": [
                  "Online Data Transfer",
                  "Offline Data Transfer",
                  "Bulk Data Migration",
                  "Incremental Transfer",
                  "Data Ingestion Pipelines",
                  "Edge-to-Cloud Gateway",
                  "Data Filtering at Source",
                  "Bandwidth-Optimized Transfer",
                  "Transfer Acceleration",
                  "Multipart Upload"
                ]
              }
            ]
          },
          {
            "domain": "Edge Security",
            "sub_domains": [
              {
                "sub_domain": "Authentication and Authorization",
                "topics": [
                  "Zero Trust Architecture",
                  "Multi-Factor Authentication (MFA)",
                  "Token-Based Authentication",
                  "OAuth 2.0",
                  "JWT (JSON Web Tokens)",
                  "API Key Management",
                  "Certificate-Based Auth",
                  "Role-Based Access Control (RBAC)",
                  "Attribute-Based Access Control (ABAC)",
                  "Principle of Least Privilege (PoLP)"
                ]
              },
              {
                "sub_domain": "Encryption and Data Protection",
                "topics": [
                  "Transport Layer Security (TLS)",
                  "End-to-End Encryption",
                  "Data-at-Rest Encryption",
                  "Data-in-Transit Encryption",
                  "Key Management",
                  "Certificate Management",
                  "SSL/TLS Termination",
                  "Crypto Key Rotation",
                  "Hardware Security Modules (HSM)",
                  "Secure Enclaves"
                ]
              },
              {
                "sub_domain": "Application Security",
                "topics": [
                  "Web Application Firewall (WAF)",
                  "API Security",
                  "Bot Mitigation",
                  "Rate Limiting",
                  "DDoS Protection",
                  "Input Validation",
                  "Cross-Site Scripting (XSS) Prevention",
                  "SQL Injection Prevention",
                  "CORS Policy Management",
                  "Content Security Policy (CSP)"
                ]
              },
              {
                "sub_domain": "Network Security",
                "topics": [
                  "Firewall Rules",
                  "Network Segmentation",
                  "Virtual Private Networks (VPN)",
                  "Private Connectivity",
                  "Intrusion Detection Systems (IDS)",
                  "Intrusion Prevention Systems (IPS)",
                  "Network Access Control",
                  "Secure DNS",
                  "Traffic Inspection",
                  "Threat Intelligence"
                ]
              },
              {
                "sub_domain": "Compliance and Governance",
                "topics": [
                  "Data Sovereignty",
                  "GDPR Compliance",
                  "Data Residency Requirements",
                  "Privacy-by-Design",
                  "Audit Logging",
                  "Compliance Monitoring",
                  "Data Classification",
                  "PII Protection",
                  "Data Anonymization",
                  "Regulatory Reporting"
                ]
              },
              {
                "sub_domain": "Threat Detection and Response",
                "topics": [
                  "Security Monitoring",
                  "Anomaly Detection",
                  "Behavioral Analysis",
                  "Security Information and Event Management (SIEM)",
                  "Incident Response",
                  "Vulnerability Scanning",
                  "Penetration Testing",
                  "Security Patching",
                  "Threat Hunting",
                  "Forensic Analysis"
                ]
              }
            ]
          },
          {
            "domain": "Edge Application Development",
            "sub_domains": [
              {
                "sub_domain": "Development Tools and SDKs",
                "topics": [
                  "CLI Tools (Wrangler, etc.)",
                  "Edge SDKs",
                  "Local Development Environment",
                  "Edge Emulators",
                  "Testing Frameworks",
                  "Debugging Tools",
                  "Code Profiling",
                  "Performance Analysis",
                  "API Clients",
                  "IDE Integration"
                ]
              },
              {
                "sub_domain": "Programming Models",
                "topics": [
                  "Request-Response Pattern",
                  "Pub/Sub Messaging",
                  "Event-Driven Programming",
                  "Reactive Programming",
                  "Microservices Architecture",
                  "Service Mesh",
                  "API Gateway Pattern",
                  "Backend for Frontend (BFF)",
                  "Strangler Fig Pattern",
                  "Circuit Breaker Pattern"
                ]
              },
              {
                "sub_domain": "Edge APIs and Standards",
                "topics": [
                  "Web Standard APIs",
                  "Fetch API",
                  "WebSocket API",
                  "Streams API",
                  "Service Worker API",
                  "Cache API",
                  "Crypto API",
                  "Encoding API",
                  "Web Standards Compliance",
                  "Progressive Web Apps (PWA)"
                ]
              },
              {
                "sub_domain": "State Management",
                "topics": [
                  "Stateful Edge Computing",
                  "Durable Objects",
                  "Session Management",
                  "Distributed State",
                  "State Persistence",
                  "State Replication",
                  "Consistency Models",
                  "Conflict-Free Replicated Data Types (CRDT)",
                  "Actor Model",
                  "Workflow Orchestration"
                ]
              },
              {
                "sub_domain": "Deployment and CI/CD",
                "topics": [
                  "Continuous Integration",
                  "Continuous Deployment",
                  "Git-Based Workflows",
                  "Automated Testing",
                  "Canary Deployments",
                  "Blue-Green Deployment",
                  "Gradual Rollouts",
                  "Rollback Strategies",
                  "Version Control",
                  "Infrastructure as Code (IaC)"
                ]
              },
              {
                "sub_domain": "Edge-Specific Optimizations",
                "topics": [
                  "Bundle Size Optimization",
                  "Code Splitting",
                  "Tree Shaking",
                  "Lazy Loading",
                  "Resource Hints",
                  "Critical CSS",
                  "Above-the-Fold Optimization",
                  "Memory Management",
                  "CPU Time Optimization",
                  "Execution Time Limits"
                ]
              }
            ]
          },
          {
            "domain": "Edge AI and Machine Learning",
            "sub_domains": [
              {
                "sub_domain": "Model Deployment",
                "topics": [
                  "Model Optimization",
                  "Model Quantization",
                  "Model Pruning",
                  "Model Compilation",
                  "ONNX Format",
                  "TensorFlow Lite",
                  "Edge Inference Engines",
                  "Model Versioning",
                  "A/B Testing Models",
                  "Model Rollout Strategies"
                ]
              },
              {
                "sub_domain": "Inference at the Edge",
                "topics": [
                  "Real-Time Inference",
                  "Batch Inference",
                  "Low-Latency Inference",
                  "GPU-Accelerated Inference",
                  "Hardware Acceleration",
                  "Inference Optimization",
                  "Model Serving",
                  "Inference Caching",
                  "Fallback Strategies",
                  "Inference Monitoring"
                ]
              },
              {
                "sub_domain": "Edge ML Frameworks",
                "topics": [
                  "TensorFlow at Edge",
                  "PyTorch Mobile",
                  "NVIDIA Triton Inference Server",
                  "NVIDIA TAO Toolkit",
                  "OpenVINO",
                  "Core ML",
                  "ML.NET",
                  "Apache TVM",
                  "Edge Impulse",
                  "Custom ML Runtimes"
                ]
              },
              {
                "sub_domain": "Computer Vision at Edge",
                "topics": [
                  "Image Classification",
                  "Object Detection",
                  "Semantic Segmentation",
                  "Face Recognition",
                  "Optical Character Recognition (OCR)",
                  "Video Analytics",
                  "Motion Detection",
                  "Pose Estimation",
                  "Image Enhancement",
                  "Real-Time Video Processing"
                ]
              },
              {
                "sub_domain": "Natural Language Processing",
                "topics": [
                  "Text Classification",
                  "Sentiment Analysis",
                  "Named Entity Recognition (NER)",
                  "Language Models at Edge",
                  "Speech Recognition",
                  "Text-to-Speech",
                  "Translation Services",
                  "Tokenization",
                  "Embedding Models",
                  "Vector Search"
                ]
              },
              {
                "sub_domain": "ML Operations (MLOps)",
                "topics": [
                  "Model Lifecycle Management",
                  "Model Registry",
                  "Feature Store",
                  "Model Monitoring",
                  "Drift Detection",
                  "Performance Metrics",
                  "Model Retraining Triggers",
                  "Automated Model Updates",
                  "Edge Fleet Management",
                  "Federated Learning"
                ]
              }
            ]
          },
          {
            "domain": "Edge Observability and Monitoring",
            "sub_domains": [
              {
                "sub_domain": "Metrics Collection",
                "topics": [
                  "Performance Metrics",
                  "Resource Utilization Metrics",
                  "Request Metrics",
                  "Error Rate Tracking",
                  "Latency Measurements",
                  "Throughput Monitoring",
                  "Cache Performance Metrics",
                  "Custom Metrics",
                  "Time-Series Data",
                  "Metric Aggregation"
                ]
              },
              {
                "sub_domain": "Logging",
                "topics": [
                  "Structured Logging",
                  "Log Aggregation",
                  "Log Streaming",
                  "Log Retention Policies",
                  "Log Analysis",
                  "Log Search and Query",
                  "Error Logging",
                  "Audit Logs",
                  "Access Logs",
                  "Debug Logging"
                ]
              },
              {
                "sub_domain": "Distributed Tracing",
                "topics": [
                  "Request Tracing",
                  "Span Generation",
                  "Trace Context Propagation",
                  "OpenTelemetry",
                  "Jaeger Integration",
                  "Zipkin Integration",
                  "Service Dependency Mapping",
                  "Latency Attribution",
                  "Root Cause Analysis",
                  "Trace Sampling"
                ]
              },
              {
                "sub_domain": "Alerting and Notifications",
                "topics": [
                  "Alert Rules Configuration",
                  "Threshold-Based Alerts",
                  "Anomaly-Based Alerts",
                  "Alert Routing",
                  "Notification Channels",
                  "On-Call Management",
                  "Alert Escalation",
                  "Alert Suppression",
                  "Alert History",
                  "SLA Monitoring"
                ]
              },
              {
                "sub_domain": "Performance Monitoring",
                "topics": [
                  "Real User Monitoring (RUM)",
                  "Synthetic Monitoring",
                  "Application Performance Monitoring (APM)",
                  "Core Web Vitals",
                  "Time to First Byte (TTFB)",
                  "First Contentful Paint (FCP)",
                  "Largest Contentful Paint (LCP)",
                  "Cumulative Layout Shift (CLS)",
                  "First Input Delay (FID)",
                  "Response Time Analysis"
                ]
              },
              {
                "sub_domain": "Diagnostics and Troubleshooting",
                "topics": [
                  "Health Checks",
                  "Status Pages",
                  "Incident Management",
                  "Postmortem Analysis",
                  "Performance Profiling",
                  "Memory Profiling",
                  "Network Diagnostics",
                  "Error Tracking",
                  "Stack Traces",
                  "Debug Mode"
                ]
              }
            ]
          },
          {
            "domain": "Edge Content Delivery",
            "sub_domains": [
              {
                "sub_domain": "Static Content Delivery",
                "topics": [
                  "Image Delivery",
                  "CSS/JavaScript Delivery",
                  "Font Delivery",
                  "Static Site Hosting",
                  "Asset Optimization",
                  "WebP Conversion",
                  "AVIF Support",
                  "Responsive Images",
                  "Image Resizing",
                  "Format Negotiation"
                ]
              },
              {
                "sub_domain": "Dynamic Content Delivery",
                "topics": [
                  "Edge-Side Rendering",
                  "Personalized Content",
                  "Content Assembly",
                  "A/B Testing at Edge",
                  "Feature Flags",
                  "Content Stitching",
                  "Template Rendering",
                  "Server-Side Rendering (SSR)",
                  "Incremental Static Regeneration (ISR)",
                  "Edge-Side Includes (ESI)"
                ]
              },
              {
                "sub_domain": "Video Streaming",
                "topics": [
                  "HTTP Live Streaming (HLS)",
                  "Dynamic Adaptive Streaming (DASH)",
                  "Video Transcoding",
                  "Adaptive Bitrate Streaming (ABR)",
                  "Live Video Streaming",
                  "Video-on-Demand (VOD)",
                  "Low-Latency Streaming",
                  "Stream Packaging",
                  "DRM Integration",
                  "Thumbnail Generation"
                ]
              },
              {
                "sub_domain": "Media Processing",
                "topics": [
                  "Image Transformation",
                  "Video Optimization",
                  "Audio Processing",
                  "Format Conversion",
                  "Quality Adjustment",
                  "Watermarking",
                  "Content Moderation",
                  "Metadata Extraction",
                  "Thumbnail Creation",
                  "Frame Extraction"
                ]
              },
              {
                "sub_domain": "Content Protection",
                "topics": [
                  "Digital Rights Management (DRM)",
                  "Token Authentication",
                  "Signed URLs",
                  "Geo-Blocking",
                  "IP Whitelisting",
                  "Referrer Validation",
                  "Time-Based Access Control",
                  "Content Encryption",
                  "Watermark Verification",
                  "Hotlink Protection"
                ]
              },
              {
                "sub_domain": "Content Optimization",
                "topics": [
                  "Automatic Compression",
                  "Smart Quality Selection",
                  "Client Hints",
                  "Network-Aware Delivery",
                  "Device-Aware Delivery",
                  "Progressive Enhancement",
                  "Lazy Loading Strategies",
                  "Priority Hints",
                  "Resource Prioritization",
                  "Preload/Prefetch"
                ]
              }
            ]
          },
          {
            "domain": "Edge Data Processing and Analytics",
            "sub_domains": [
              {
                "sub_domain": "Stream Processing",
                "topics": [
                  "Real-Time Stream Processing",
                  "Event Stream Processing",
                  "Complex Event Processing (CEP)",
                  "Stream Windowing",
                  "Stream Joins",
                  "Stream Aggregation",
                  "Kafka Integration",
                  "Message Queue Processing",
                  "Backpressure Handling",
                  "Stream State Management"
                ]
              },
              {
                "sub_domain": "Real-Time Analytics",
                "topics": [
                  "Edge Analytics",
                  "Time-Series Analysis",
                  "Aggregation Pipelines",
                  "Statistical Analysis",
                  "Pattern Recognition",
                  "Trend Detection",
                  "Forecasting",
                  "Outlier Detection",
                  "Data Visualization",
                  "Dashboard Integration"
                ]
              },
              {
                "sub_domain": "Data Transformation",
                "topics": [
                  "ETL at the Edge",
                  "Data Cleaning",
                  "Data Enrichment",
                  "Data Normalization",
                  "Schema Mapping",
                  "Format Conversion",
                  "Data Validation",
                  "Field Extraction",
                  "Data Masking",
                  "Data Aggregation"
                ]
              },
              {
                "sub_domain": "Edge IoT Data Processing",
                "topics": [
                  "Sensor Data Processing",
                  "Telemetry Data Handling",
                  "Time-Series Data Management",
                  "Data Sampling",
                  "Data Filtering",
                  "Data Compression",
                  "Protocol Translation",
                  "Device Twin Synchronization",
                  "Shadow State Management",
                  "Command and Control"
                ]
              },
              {
                "sub_domain": "Batch Processing at Edge",
                "topics": [
                  "Scheduled Jobs",
                  "Cron Triggers",
                  "Batch Data Processing",
                  "Offline Processing",
                  "Data Backfill",
                  "Report Generation",
                  "Data Export",
                  "Bulk Operations",
                  "Job Scheduling",
                  "Workflow Automation"
                ]
              }
            ]
          },
          {
            "domain": "Edge Platform Services",
            "sub_domains": [
              {
                "sub_domain": "Message Queues and Pub/Sub",
                "topics": [
                  "Message Queue Services",
                  "Publish/Subscribe Systems",
                  "Event Bus",
                  "Message Routing",
                  "Queue Management",
                  "Dead Letter Queues",
                  "Message Persistence",
                  "At-Least-Once Delivery",
                  "Exactly-Once Semantics",
                  "Message Ordering"
                ]
              },
              {
                "sub_domain": "Edge Communication Services",
                "topics": [
                  "WebRTC Infrastructure",
                  "TURN Servers",
                  "SFU (Selective Forwarding Unit)",
                  "Real-Time Communications",
                  "Video Conferencing",
                  "Live Chat Services",
                  "Push Notifications",
                  "Email Services",
                  "SMS Gateway",
                  "Voice Services"
                ]
              },
              {
                "sub_domain": "API Management",
                "topics": [
                  "API Gateway",
                  "API Rate Limiting",
                  "API Versioning",
                  "API Documentation",
                  "API Key Management",
                  "Request/Response Transformation",
                  "API Caching",
                  "API Analytics",
                  "GraphQL Support",
                  "REST API Management"
                ]
              },
              {
                "sub_domain": "Edge Automation Services",
                "topics": [
                  "Workflow Engines",
                  "Task Scheduling",
                  "Event-Driven Automation",
                  "Webhook Handlers",
                  "Integration Services",
                  "Orchestration Workflows",
                  "State Machines",
                  "Business Process Automation",
                  "Retry Logic",
                  "Error Handling"
                ]
              },
              {
                "sub_domain": "Edge Search and Discovery",
                "topics": [
                  "Full-Text Search",
                  "Vector Search",
                  "Semantic Search",
                  "Search Indexing",
                  "Faceted Search",
                  "Auto-Complete",
                  "Search Ranking",
                  "Search Analytics",
                  "Service Discovery",
                  "API Discovery"
                ]
              }
            ]
          },
          {
            "domain": "Edge Reliability and Resilience",
            "sub_domains": [
              {
                "sub_domain": "High Availability",
                "topics": [
                  "Multi-Region Deployment",
                  "Active-Active Architecture",
                  "Active-Passive Failover",
                  "Geographic Redundancy",
                  "Redundant Network Paths",
                  "Service Redundancy",
                  "Automatic Failover",
                  "Load Distribution",
                  "Health-Based Routing",
                  "Disaster Recovery"
                ]
              },
              {
                "sub_domain": "Load Balancing",
                "topics": [
                  "Global Load Balancing",
                  "Local Load Balancing",
                  "Round-Robin Algorithms",
                  "Least Connections",
                  "Weighted Distribution",
                  "IP Hash",
                  "Geographic Load Balancing",
                  "Layer 4 Load Balancing",
                  "Layer 7 Load Balancing",
                  "Session Affinity"
                ]
              },
              {
                "sub_domain": "Fault Tolerance",
                "topics": [
                  "Error Recovery",
                  "Graceful Degradation",
                  "Circuit Breaker Pattern",
                  "Retry Mechanisms",
                  "Timeout Management",
                  "Bulkhead Pattern",
                  "Fallback Strategies",
                  "Self-Healing Systems",
                  "Chaos Engineering",
                  "Fault Injection Testing"
                ]
              },
              {
                "sub_domain": "Traffic Management",
                "topics": [
                  "Traffic Splitting",
                  "Canary Releases",
                  "Shadow Traffic",
                  "Traffic Mirroring",
                  "Request Routing",
                  "Weighted Routing",
                  "Traffic Shaping",
                  "Queue Management",
                  "Admission Control",
                  "Overload Protection"
                ]
              },
              {
                "sub_domain": "Service Level Management",
                "topics": [
                  "Service Level Agreements (SLA)",
                  "Service Level Objectives (SLO)",
                  "Service Level Indicators (SLI)",
                  "Uptime Guarantees",
                  "Performance Guarantees",
                  "Error Budget",
                  "Availability Metrics",
                  "Reliability Metrics",
                  "Mean Time to Recovery (MTTR)",
                  "Mean Time Between Failures (MTBF)"
                ]
              },
              {
                "sub_domain": "Waiting Room and Queueing",
                "topics": [
                  "Virtual Waiting Rooms",
                  "Queue Management",
                  "Token-Based Admission",
                  "Fair Queueing",
                  "Priority Queueing",
                  "Throttling Mechanisms",
                  "Surge Protection",
                  "Flash Traffic Handling",
                  "Queue Position Tracking",
                  "Estimated Wait Time"
                ]
              }
            ]
          },
          {
            "domain": "Edge Use Cases and Applications",
            "sub_domains": [
              {
                "sub_domain": "Internet of Things (IoT)",
                "topics": [
                  "Smart Home Devices",
                  "Industrial IoT (IIoT)",
                  "Connected Vehicles",
                  "Autonomous Vehicles",
                  "Smart Cities",
                  "Environmental Monitoring",
                  "Asset Tracking",
                  "Predictive Maintenance",
                  "Remote Monitoring",
                  "Fleet Management"
                ]
              },
              {
                "sub_domain": "Media and Entertainment",
                "topics": [
                  "OTT Streaming",
                  "Live Sports Broadcasting",
                  "Gaming (Cloud Gaming)",
                  "Interactive Video",
                  "Content Personalization",
                  "Ad Insertion",
                  "Digital Rights Management",
                  "Multi-CDN Strategy",
                  "Video Analytics",
                  "User Experience Optimization"
                ]
              },
              {
                "sub_domain": "E-Commerce and Retail",
                "topics": [
                  "Personalized Shopping",
                  "Real-Time Inventory",
                  "Dynamic Pricing",
                  "Shopping Cart Optimization",
                  "Fraud Detection",
                  "Checkout Optimization",
                  "Product Recommendations",
                  "Search Optimization",
                  "Flash Sales Management",
                  "Omnichannel Experience"
                ]
              },
              {
                "sub_domain": "Healthcare and Telemedicine",
                "topics": [
                  "Remote Patient Monitoring",
                  "Medical Imaging Processing",
                  "Real-Time Diagnostics",
                  "Telehealth Platforms",
                  "Wearable Device Integration",
                  "Health Data Analytics",
                  "Emergency Response Systems",
                  "Clinical Decision Support",
                  "Patient Data Privacy",
                  "Medical Device Connectivity"
                ]
              },
              {
                "sub_domain": "Industrial and Manufacturing",
                "topics": [
                  "Factory Automation",
                  "Quality Control Systems",
                  "Supply Chain Optimization",
                  "Robotics Integration",
                  "Production Line Monitoring",
                  "Equipment Health Monitoring",
                  "Energy Management",
                  "Safety Systems",
                  "Digital Twin Integration",
                  "Process Optimization"
                ]
              },
              {
                "sub_domain": "Smart Infrastructure",
                "topics": [
                  "Smart Grid Management",
                  "Traffic Management Systems",
                  "Public Safety Systems",
                  "Smart Building Automation",
                  "Parking Management",
                  "Waste Management",
                  "Water Management",
                  "Lighting Control",
                  "Environmental Sensors",
                  "Infrastructure Monitoring"
                ]
              },
              {
                "sub_domain": "Finance and FinTech",
                "topics": [
                  "Real-Time Fraud Detection",
                  "High-Frequency Trading",
                  "Payment Processing",
                  "Risk Assessment",
                  "Customer Authentication",
                  "Transaction Monitoring",
                  "Regulatory Compliance",
                  "Personalized Banking",
                  "Credit Scoring",
                  "Cryptocurrency Processing"
                ]
              },
              {
                "sub_domain": "Augmented and Virtual Reality",
                "topics": [
                  "AR Content Delivery",
                  "VR Streaming",
                  "Low-Latency Rendering",
                  "Spatial Computing",
                  "3D Model Delivery",
                  "Real-Time Interaction",
                  "Motion Tracking",
                  "Haptic Feedback",
                  "Immersive Experiences",
                  "Mixed Reality Applications"
                ]
              }
            ]
          },
          {
            "domain": "Edge Platform Economics and Operations",
            "sub_domains": [
              {
                "sub_domain": "Cost Management",
                "topics": [
                  "Usage-Based Billing",
                  "Resource Allocation",
                  "Cost Optimization",
                  "Egress Cost Management",
                  "Storage Cost Optimization",
                  "Compute Cost Management",
                  "Request-Based Pricing",
                  "Bandwidth Pricing",
                  "Reserved Capacity",
                  "Cost Monitoring and Alerts"
                ]
              },
              {
                "sub_domain": "Resource Management",
                "topics": [
                  "Capacity Planning",
                  "Resource Provisioning",
                  "Auto-Scaling Policies",
                  "Resource Quotas",
                  "Resource Limits",
                  "Throttling Policies",
                  "Priority Classes",
                  "Resource Reservation",
                  "Multi-Tenancy",
                  "Resource Isolation"
                ]
              },
              {
                "sub_domain": "Platform Governance",
                "topics": [
                  "Access Control Policies",
                  "Organizational Units",
                  "Policy Management",
                  "Compliance Frameworks",
                  "Audit Trails",
                  "Change Management",
                  "Configuration Management",
                  "Service Catalogs",
                  "Approval Workflows",
                  "Tag Management"
                ]
              },
              {
                "sub_domain": "Vendor Management",
                "topics": [
                  "Multi-CDN Strategies",
                  "Vendor Selection Criteria",
                  "Service Level Agreements",
                  "Vendor Lock-In Mitigation",
                  "Cost Comparison",
                  "Performance Benchmarking",
                  "Migration Strategies",
                  "Hybrid Deployments",
                  "Failover Between Vendors",
                  "Contract Negotiation"
                ]
              },
              {
                "sub_domain": "Operational Excellence",
                "topics": [
                  "DevOps Practices",
                  "Site Reliability Engineering (SRE)",
                  "Automation Strategies",
                  "Documentation",
                  "Runbooks",
                  "Standard Operating Procedures",
                  "Training and Onboarding",
                  "Knowledge Management",
                  "Best Practices",
                  "Continuous Improvement"
                ]
              }
            ]
          }
        ]
      }
    }
  ]
}